anyplayer/__init__.py
anyplayer/dicts.py
anyplayer/p_auto.py
anyplayer/p_cl.py
anyplayer/p_player.py
anyplayer/p_process.py
anyplayer/player_aplay.py
anyplayer/player_cmus.py
anyplayer/player_elisa.py
anyplayer/player_ffplay.py
anyplayer/player_filemgr.py
anyplayer/player_gst.py
anyplayer/player_mpg123.py
anyplayer/player_mpv.py
anyplayer/player_playsound.py
anyplayer/player_pyaudio.py
anyplayer/player_simpleaudio.py
anyplayer/player_vlc.py
anyplayer/players.py
anyplayer/utils.py
anyplayer-0.0.7.dist-info/LICENSE
anyplayer-0.0.7.dist-info/METADATA
anyplayer-0.0.7.dist-info/WHEEL
anyplayer-0.0.7.dist-info/top_level.txt
anyplayer-0.0.7.dist-info/RECORD
