Metadata-Version: 2.1
Name: anyplayer
Version: 0.0.7
Summary: A simple, minimal-hassle, few-dependency Python audio playback solution
Author-email: userElaina <userelaina@pm.me>
Maintainer-email: userElaina <userelaina@pm.me>
License: MIT License
Project-URL: Homepage, https://github.com/userElaina/anyplayer
Project-URL: Bug Reports, https://github.com/userElaina/anyplayer/issues
Project-URL: Source, https://github.com/userElaina/anyplayer
Keywords: audio
Classifier: License :: OSI Approved :: MIT License
Classifier: Programming Language :: Python :: 3
Requires-Python: >=3.7
License-File: LICENSE
Provides-Extra: dev
Requires-Dist: simpleaudio; extra == "dev"
Requires-Dist: pyaudio; extra == "dev"
Requires-Dist: playsound3; extra == "dev"
